excel_graph_parser/__init__.py
excel_graph_parser/graph_parser.py
excel_graph_parser/parser.py
excel_graph_parser-0.2.1.dist-info/LICENSE
excel_graph_parser-0.2.1.dist-info/METADATA
excel_graph_parser-0.2.1.dist-info/WHEEL
excel_graph_parser-0.2.1.dist-info/top_level.txt
excel_graph_parser-0.2.1.dist-info/RECORD
