Metadata-Version: 2.1
Name: excel_graph_parser
Version: 0.2.1
Summary: Parser to translate excel graphs to Plotly figures
Author-email: VIKTOR <support@viktor.ai>
Maintainer-email: VIKTOR <support@viktor.ai>
License: MIT License
Project-URL: Homepage, https://github.com/viktor-platform/excel_graph_parser
Project-URL: Bug Reports, https://github.com/viktor-platform/excel_graph_parser/issues
Requires-Python: >=3.8
License-File: LICENSE
Requires-Dist: viktor
Requires-Dist: openpyxl
Requires-Dist: plotly
